steampipe_alchemy/__init__.py
steampipe_alchemy/db.py
steampipe_alchemy/mixins/__init__.py
steampipe_alchemy/mixins/format.py
steampipe_alchemy/models/__init__.py
steampipe_alchemy/models/aws_account.py
steampipe_alchemy/models/aws_acm_certificate.py
steampipe_alchemy/models/aws_api_gateway_api_key.py
steampipe_alchemy/models/aws_api_gateway_authorizer.py
steampipe_alchemy/models/aws_api_gateway_rest_api.py
steampipe_alchemy/models/aws_api_gateway_stage.py
steampipe_alchemy/models/aws_api_gateway_usage_plan.py
steampipe_alchemy/models/aws_api_gatewayv2_api.py
steampipe_alchemy/models/aws_api_gatewayv2_domain_name.py
steampipe_alchemy/models/aws_api_gatewayv2_stage.py
steampipe_alchemy/models/aws_availability_zone.py
steampipe_alchemy/models/aws_backup_plan.py
steampipe_alchemy/models/aws_backup_vault.py
steampipe_alchemy/models/aws_cloudformation_stack.py
steampipe_alchemy/models/aws_cloudtrail_trail.py
steampipe_alchemy/models/aws_cloudwatch_alarm.py
steampipe_alchemy/models/aws_cloudwatch_log_group.py
steampipe_alchemy/models/aws_cloudwatch_log_metric_filter.py
steampipe_alchemy/models/aws_cloudwatch_log_stream.py
steampipe_alchemy/models/aws_codebuild_project.py
steampipe_alchemy/models/aws_config_configuration_recorder.py
steampipe_alchemy/models/aws_config_conformance_pack.py
steampipe_alchemy/models/aws_dynamodb_backup.py
steampipe_alchemy/models/aws_dynamodb_global_table.py
steampipe_alchemy/models/aws_dynamodb_table.py
steampipe_alchemy/models/aws_ebs_snapshot.py
steampipe_alchemy/models/aws_ebs_volume.py
steampipe_alchemy/models/aws_ec2_ami.py
steampipe_alchemy/models/aws_ec2_application_load_balancer.py
steampipe_alchemy/models/aws_ec2_autoscaling_group.py
steampipe_alchemy/models/aws_ec2_classic_load_balancer.py
steampipe_alchemy/models/aws_ec2_gateway_load_balancer.py
steampipe_alchemy/models/aws_ec2_instance.py
steampipe_alchemy/models/aws_ec2_instance_availability.py
steampipe_alchemy/models/aws_ec2_instance_type.py
steampipe_alchemy-0.1.6.dist-info/AUTHORS.rst
steampipe_alchemy-0.1.6.dist-info/LICENSE
steampipe_alchemy-0.1.6.dist-info/METADATA
steampipe_alchemy-0.1.6.dist-info/WHEEL
steampipe_alchemy-0.1.6.dist-info/top_level.txt
steampipe_alchemy-0.1.6.dist-info/RECORD
