Metadata-Version: 2.1
Name: steampipe-alchemy
Version: 0.1.6
Summary: Python Boilerplate contains all the boilerplate you need to create a Python package.
Home-page: https://github.com/RyanJarv/steampipe_alchemy
Author: Ryan Gerstenkorn
Author-email: ryan.gerstenkorn@rhinosecuritylabs.com
License: BSD license
Keywords: steampipe_alchemy
Platform: UNKNOWN
Classifier: Development Status :: 2 - Pre-Alpha
Classifier: Intended Audience :: Developers
Classifier: License :: OSI Approved :: BSD License
Classifier: Natural Language :: English
Classifier: Programming Language :: Python :: 3
Classifier: Programming Language :: Python :: 3.6
Classifier: Programming Language :: Python :: 3.7
Classifier: Programming Language :: Python :: 3.8
Classifier: Programming Language :: Python :: 3.9
Requires-Python: >=3.5
Requires-Dist: psycopg2 (>=2.0)
Requires-Dist: SQLAlchemy (>=1.0)
Requires-Dist: typing-extensions (>=3.0)
